wellcadformats/__init__.py
wellcadformats/arraydata.py
wellcadformats/curvedata.py
wellcadformats/sonicgui.py
wellcadformats/wa.py
wellcadformats-0.3.dist-info/METADATA
wellcadformats-0.3.dist-info/WHEEL
wellcadformats-0.3.dist-info/entry_points.txt
wellcadformats-0.3.dist-info/top_level.txt
wellcadformats-0.3.dist-info/RECORD
