Metadata-Version: 2.1
Name: wellcadformats
Version: 0.3
Summary: Read/write WellCAD's ASCII data file formats
Author-email: "Kent Inverarity (SA Govt)" <kent.inverarity@sa.gov.au>
Project-URL: Homepage, https://github.com/dew-waterscience/wellcadformats
Project-URL: Bug Tracker, https://github.com/dew-waterscience/wellcadformats/issues
Keywords: science,geophysics
Classifier: Development Status :: 4 - Beta
Classifier: Environment :: Console
Classifier: Intended Audience :: Customer Service
Classifier: Intended Audience :: Developers
Classifier: Intended Audience :: Education
Classifier: Intended Audience :: End Users/Desktop
Classifier: Intended Audience :: Other Audience
Classifier: Intended Audience :: Science/Research
Classifier: Natural Language :: English
Classifier: Operating System :: OS Independent
Classifier: Programming Language :: Python :: 2.6
Classifier: Programming Language :: Python :: 2.7
Classifier: Programming Language :: Python :: 3
Classifier: Programming Language :: Python :: 3.2
Classifier: Programming Language :: Python :: 3.3
Classifier: Programming Language :: Python :: 3.4
Classifier: Topic :: Scientific/Engineering
Classifier: Topic :: System :: Filesystems
Classifier: Topic :: Scientific/Engineering :: Information Analysis
Requires-Python: >=3.7
Requires-Dist: pandas
Requires-Dist: numpy
